collective/__init__.py
collective/glossary/__init__.py
collective/glossary/config.py
collective/glossary/configure.zcml
collective/glossary/content.py
collective/glossary/controlpanel.py
collective/glossary/indexers.py
collective/glossary/interfaces.py
collective/glossary/logger.py
collective/glossary/profiles.zcml
collective/glossary/setuphandlers.py
collective/glossary/testing.py
collective/glossary/utils.py
collective/glossary/vocabulary.py
collective/glossary/vocabulary.zcml
collective/glossary/Extensions/Install.py
collective/glossary/Extensions/__init__.py
collective/glossary/api/__init__.py
collective/glossary/api/configure.zcml
collective/glossary/api/services/__init__.py
collective/glossary/api/services/configure.zcml
collective/glossary/api/services/glossary/__init__.py
collective/glossary/api/services/glossary/configure.zcml
collective/glossary/api/services/glossary/get.py
collective/glossary/browser/__init__.py
collective/glossary/browser/configure.zcml
collective/glossary/browser/views.py
collective/glossary/browser/static/glossary-icon.png
collective/glossary/browser/static/jquery.glossarize.js
collective/glossary/browser/static/main.css
collective/glossary/browser/static/main.js
collective/glossary/browser/static/term-icon.png
collective/glossary/browser/static/tooltip.css
collective/glossary/browser/static/tooltip.js
collective/glossary/browser/templates/glossary.pt
collective/glossary/browser/templates/term.pt
collective/glossary/browser/viewlets/__init__.py
collective/glossary/browser/viewlets/configure.zcml
collective/glossary/browser/viewlets/css_js.pt
collective/glossary/browser/viewlets/viewlets.py
collective/glossary/locales/__main__.py
collective/glossary/locales/collective.glossary.pot
collective/glossary/locales/de/LC_MESSAGES/collective.glossary.po
collective/glossary/locales/en/LC_MESSAGES/collective.glossary.po
collective/glossary/locales/nl/LC_MESSAGES/collective.glossary.po
collective/glossary/profiles/default/browserlayer.xml
collective_glossary-3.0.1.dist-info/METADATA
collective_glossary-3.0.1.dist-info/WHEEL
collective_glossary-3.0.1.dist-info/entry_points.txt
collective_glossary-3.0.1.dist-info/licenses/LICENSE.GPL
collective_glossary-3.0.1.dist-info/licenses/LICENSE.md
collective_glossary-3.0.1.dist-info/RECORD
