Metadata-Version: 2.4
Name: collective.glossary
Version: 3.0.1
Summary: Content types to define a glossary and its terms
Project-URL: Homepage, https://github.com/collective/collective.glossary
Project-URL: PyPI, https://pypi.org/project/collective.glossary
Project-URL: Source, https://github.com/collective/collective.glossary
Project-URL: Tracker, https://github.com/collective/collective.glossary/issues
Author-email: Plone Community <collective@plone.org>
License-Expression: GPL-2.0-only
License-File: LICENSE.GPL
License-File: LICENSE.md
Keywords: CMS,Plone,Python
Classifier: Development Status :: 3 - Alpha
Classifier: Environment :: Web Environment
Classifier: Framework :: Plone
Classifier: Framework :: Plone :: 6.0
Classifier: Framework :: Plone :: 6.1
Classifier: Framework :: Plone :: Addon
Classifier: License :: OSI Approved :: GNU General Public License v2 (GPLv2)
Classifier: Operating System :: OS Independent
Classifier: Programming Language :: Python
Classifier: Programming Language :: Python :: 3.10
Classifier: Programming Language :: Python :: 3.11
Classifier: Programming Language :: Python :: 3.12
Classifier: Programming Language :: Python :: 3.13
Requires-Python: >=3.10
Requires-Dist: plone-api
Requires-Dist: plone-restapi
Requires-Dist: plone-volto
Requires-Dist: products-cmfplone
Provides-Extra: dev
Requires-Dist: zest-releaser[recommended]>=9.1.3; extra == 'dev'
Requires-Dist: zestreleaser-towncrier>=1.3.0; extra == 'dev'
Provides-Extra: test
Requires-Dist: horse-with-no-namespace; extra == 'test'
Requires-Dist: plone-app-testing; extra == 'test'
Requires-Dist: plone-restapi[test]; extra == 'test'
Requires-Dist: pytest; extra == 'test'
Requires-Dist: pytest-cov; extra == 'test'
Requires-Dist: pytest-plone>=0.5.0; extra == 'test'
